honeybee_radiance/__init__.py
honeybee_radiance/__main__.py
honeybee_radiance/_extend_honeybee.py
honeybee_radiance/config.json
honeybee_radiance/config.py
honeybee_radiance/dictutil.py
honeybee_radiance/lightpath.py
honeybee_radiance/luminaire.py
honeybee_radiance/modifierset.py
honeybee_radiance/mutil.py
honeybee_radiance/primitive.py
honeybee_radiance/putil.py
honeybee_radiance/reader.py
honeybee_radiance/sensor.py
honeybee_radiance/sensorgrid.py
honeybee_radiance/view.py
honeybee_radiance/writer.py
honeybee_radiance/cli/__init__.py
honeybee_radiance/cli/dc.py
honeybee_radiance/cli/edit.py
honeybee_radiance/cli/glare.py
honeybee_radiance/cli/grid.py
honeybee_radiance/cli/lib.py
honeybee_radiance/cli/modifier.py
honeybee_radiance/cli/mtx.py
honeybee_radiance/cli/multiphase.py
honeybee_radiance/cli/octree.py
honeybee_radiance/cli/postprocess.py
honeybee_radiance/cli/raytrace.py
honeybee_radiance/cli/rpict.py
honeybee_radiance/cli/schedule.py
honeybee_radiance/cli/setconfig.py
honeybee_radiance/cli/sky.py
honeybee_radiance/cli/study.py
honeybee_radiance/cli/sunpath.py
honeybee_radiance/cli/threephase.py
honeybee_radiance/cli/translate.py
honeybee_radiance/cli/util.py
honeybee_radiance/cli/view.py
honeybee_radiance/cli/viewfactor.py
honeybee_radiance/dynamic/__init__.py
honeybee_radiance/dynamic/group.py
honeybee_radiance/dynamic/multiphase.py
honeybee_radiance/dynamic/state.py
honeybee_radiance/dynamic/stategeo.py
honeybee_radiance/geometry/__init__.py
honeybee_radiance/geometry/bubble.py
honeybee_radiance/geometry/cone.py
honeybee_radiance/geometry/cup.py
honeybee_radiance/geometry/cylinder.py
honeybee_radiance/geometry/geometrybase.py
honeybee_radiance/geometry/instance.py
honeybee_radiance/geometry/mesh.py
honeybee_radiance/geometry/polygon.py
honeybee_radiance/geometry/ring.py
honeybee_radiance/geometry/source.py
honeybee_radiance/geometry/sphere.py
honeybee_radiance/geometry/tube.py
honeybee_radiance/lib/__init__.py
honeybee_radiance/lib/_loadmodifiers.py
honeybee_radiance-1.66.227.dist-info/licenses/LICENSE
honeybee_radiance-1.66.227.dist-info/METADATA
honeybee_radiance-1.66.227.dist-info/WHEEL
honeybee_radiance-1.66.227.dist-info/entry_points.txt
honeybee_radiance-1.66.227.dist-info/top_level.txt
honeybee_radiance-1.66.227.dist-info/RECORD
