Metadata-Version: 2.4
Name: honeybee-radiance
Version: 1.66.227
Summary: Daylight and light simulation extension for honeybee.
Home-page: https://github.com/ladybug-tools/honeybee-radiance
Author: Ladybug Tools
Author-email: info@ladybug.tools
License: AGPL-3.0
Classifier: Programming Language :: Python :: 2.7
Classifier: Programming Language :: Python :: 3.7
Classifier: Programming Language :: Python :: 3.8
Classifier: Programming Language :: Python :: 3.9
Classifier: Programming Language :: Python :: 3.10
Classifier: Programming Language :: Python :: 3.11
Classifier: Programming Language :: Python :: 3.12
Classifier: Programming Language :: Python :: Implementation :: CPython
Classifier: Programming Language :: Python :: Implementation :: IronPython
Classifier: Operating System :: OS Independent
License-File: LICENSE
Requires-Dist: honeybee-core==1.64.12
Requires-Dist: honeybee-radiance-folder==2.11.17
Requires-Dist: honeybee-radiance-command==1.23.0
Requires-Dist: honeybee-standards==2.0.7
Dynamic: author
Dynamic: author-email
Dynamic: classifier
Dynamic: description
Dynamic: description-content-type
Dynamic: home-page
Dynamic: license
Dynamic: license-file
Dynamic: requires-dist
Dynamic: summary
